{
  "filters": [
    {
      "id": 1,
      "type": "number_source",
      "properties": {"value": "20"},
      "pins": [
        {"id": 0, "direction": "out", "data_type": "int"}
      ]
    },
    {
      "id": 2,
      "type": "multiply",
      "properties": {"factor": "5"},
      "pins": [
        {"id":0 , "direction": "in", "data_type": "int"},
        {"id":1 , "direction": "out", "data_type": "int"}

      ]
    },
    {
      "id": 3,
      "type": "console_printer",
      "properties": {},
      "pins": [
        {"id":0 , "direction": "in", "data_type": "int"}
      ]
    }
  ],
  "connections": [
    {"from_node": 1, "from_port": 0, "to_node": 2, "to_port": 0},
    {"from_node": 2, "from_port": 1, "to_node": 3, "to_port": 0}
  ]
}